{
  "id": 44784215,
  "lang": "ru",
  "summary": "**Q** — минимальный язык и компилятор без зависимостей, генерирующий x86-64/arm64-код. Компиляция <100 мкс, бинарь «Hello World» ≈ 600 байт. Поддержка Linux, macOS, Windows.\n\n### Установка\n```bash\ngit clone https://git.urbach.dev/cli/q && cd q\ngo build\nln -s $PWD/q ~/.local/bin/q\n```\n\n### Использование\n```bash\nq examples/hello            # запуск\nq build examples/hello      # компиляция\nq build ex/hello --arch arm --os windows  # кросс-компиляция\n```\n\n### Статус\nСинтаксис нестабилен; примеры и тесты в репозитории. Документация появится после стабилизации ядра.",
  "inputHash": "89943b39951d424f3781a127b3a91fa8b516df471d3ef1b3e666bd4f5a646525",
  "model": "moonshotai/kimi-k2",
  "createdISO": "2025-08-07T23:56:51.356Z"
}