{
  "id": 44799929,
  "lang": "ru",
  "summary": "- Участники вспомнили Sun SPARC-станции: кто-то до сих пор запускает SPARCbook 3000ST для презентаций, кто-то хранит старые машины как рабочие.  \n- Всплыли ностальгические истории о первых рабочих местах, «bad magic number» и «magic smoke™».  \n- Кто-то отказался от физического ретрокомпьютинга в пользу эмуляции, кто-то жалуется на шум и жор энергии старых SPARC.  \n- Плюс курьёз: диск, выброшенный в невесомости, и подключение Centronics-принтера к SCSI Mac SE.",
  "sampleComments": [
    44848218,
    44848003,
    44848458,
    44845300,
    44845435
  ],
  "inputHash": "f3d2920f42363cb657852a0975d6a29180458fc93a94aaeb3ec13697349f2b53",
  "model": "moonshotai/kimi-k2:free",
  "createdISO": "2025-08-09T19:25:44.484Z"
}