{
  "id": 44807603,
  "lang": "ru",
  "summary": "- 64-битный RISC-V дешёв (≈ $1–1,5 за F133*) и даёт широкий адресный простор, высокую вычислительную эффективность и «запас на будущее».  \n- Подходит для высокопроизводительных и сложных систем.  \n- PIC64GX1000 (производство Южная Корея) стоит от $21, но значительно мощнее.",
  "sampleComments": [
    44850030
  ],
  "inputHash": "f1daed3febb7759ffc5d20be6186a6cfdf7d2e20e48019cefb3bf3852fe7c197",
  "model": "moonshotai/kimi-k2:free",
  "createdISO": "2025-08-09T21:24:01.315Z"
}