{
  "id": 44801392,
  "lang": "ru",
  "summary": "marimo — новый open-source Python-ноутбук, в котором программа представлена графом потока данных. Это снимает главные боли Jupyter: скрытое состояние, невоспроизводимость, невозможность повторного использования и сложную поддержку.\n\n**Почему старый формат не подходит**\n\n- **Воспроизводимость**. Исследования 2019–2020 гг. показали: только 4–24 % ноутбуков на GitHub можно перезапустить без ошибок и получить те же результаты. Причина — скрытое состояние: удаление или переупорядочивание ячеек ломает выводы.  \n- **Интерактивность**. В Jupyter интерактивен процесс, но не сами данные: выделение точек на графике не возвращает датафрейм.  \n- **Поддержка и переиспользование**. Файл `.ipynb` — это JSON-блоб, не валидный Python-код; сложно версионировать в Git и переиспользовать как модуль или пайплайн.\n\n**Как marimo решает задачу**\n\n- Каждый ноутбук — корректный Python-скрипт и модуль.  \n- Граф зависимостей ячеек строится статически; изменение одной ячейки автоматически перезапускает только зависимые.  \n- Реактивность: обновление переменной мгновенно отражается во всех графиках и виджетах.  \n- Один файл можно экспортировать как приложение или запускать без ядра Jupyter.",
  "inputHash": "7ce3658582b5190a341b79e311f671d6f54ef3bca42bc26924330d2e76070910",
  "model": "moonshotai/kimi-k2:free",
  "createdISO": "2025-08-09T12:52:27.635Z"
}