{
  "id": 44810057,
  "lang": "ru",
  "summary": "- «Первичные» цвета — не абсолют, а результат биологии человеческого глаза (трёх типов колбочек); у других видов они могут быть иными.  \n- Существуют два набора примарных цветов: аддитивные (RGB для светящихся экранов) и субтрактивные (CMY/K для печати и фильтров).  \n- Колесо цветов — лишь удобная модель, а не «колесо» в физическом смысле; нагляднее использовать хроматичность-диаграмму.  \n- Английский язык располагает лишь 11 базовых цветовых терминов, поэтому «синий» и «красный» преподают легче, чем «циан» и «пурпурный».  \n- Названия цветов условны: «magenta» ≈ «purple», но подчёркивает равные доли красного и синего.",
  "sampleComments": [
    44848880,
    44849213,
    44849335,
    44849375,
    44848881
  ],
  "inputHash": "80bc4ed905bece4594b784b016282f149b0bdff1d4b5076a7abd158cfd36c4e1",
  "model": "moonshotai/kimi-k2:free",
  "createdISO": "2025-08-09T20:19:07.161Z"
}