{
  "id": 44824811,
  "lang": "ru",
  "summary": "**sbixel** — минималистичный симулятор пиксельной физики на Rust и Macroquad.  \nПроект учебный: реализует песок, воду, дым, огонь, дерево и стекло.  \nКаждый пиксель — 1×1, обрабатывается по простым правилам:  \n- песок падает;  \n- вода стекает и растекается;  \n- огонь поднимается и гаснет;  \n- дым улетает вверх;  \n- стекло неподвижно;  \n- дерево горит и превращается в уголь.  \n\nУправление:  \n- ЛКМ — рисовать выбранный элемент;  \n- ПКМ — стирать;  \n- колёсико — менять размер кисти;  \n- 1-7 — выбор материала;  \n- R — очистить экран;  \n- Space — пауза;  \n- S — сохранить PNG.  \n\nСборка: `cargo run --release`.  \nТребуется stable Rust 1.70+.",
  "inputHash": "66f77dfb094a709dc728bb04b75af172efbbed5291cc6906ba0a0c0b4b706cba",
  "model": "moonshotai/kimi-k2:free",
  "createdISO": "2025-08-11T14:28:23.719Z"
}