{
  "id": 44822730,
  "lang": "ru",
  "summary": "- Французское агентство IGN опубликовало высокодетальные (20 точек/м²) LIDAR-данные Виадука Мийо.  \n- Участники делятся впечатлениями: мост впечатляет вживую, экономит время, избавляя от узких горных дорог.  \n- Отмечена красивая тень в солнечную погоду и удобство для местных жителей.  \n- Упомянуты забавные случаи: ошибочный заезд с оплатой, детские воспоминания о пробках в долине.  \n- Разобрана этимология слова Bézier и множественное число plateau → plateaux.",
  "sampleComments": [
    44863278,
    44862447,
    44862189,
    44862717,
    44863225
  ],
  "inputHash": "a74d505d378b0015498690d8048472d71ec62a3451866797a83a2d1c896173f9",
  "model": "moonshotai/kimi-k2:free",
  "createdISO": "2025-08-11T12:53:44.767Z"
}