{
  "id": 44834570,
  "lang": "en",
  "tags": [
    {
      "name": "skiing"
    },
    {
      "name": "backcountry"
    },
    {
      "name": "splittboard"
    },
    {
      "name": "hiking"
    },
    {
      "name": "mountaineering"
    },
    {
      "name": "gear"
    },
    {
      "name": "safety"
    },
    {
      "name": "trails"
    },
    {
      "name": "outdoor"
    },
    {
      "name": "adventure"
    }
  ],
  "inputHash": "c0a36c388ef3e27ce4c6e166795abd3b7ecfd0bf8637435acf81ed4c4d1d5a57",
  "model": "mistralai/mistral-small-3.2-24b-instruct:free",
  "createdISO": "2025-08-15T13:44:25.308Z"
}