{
  "id": 44836294,
  "lang": "ru",
  "summary": "- Экран обновляется быстро, но с заметным «ghosting» (на примере с котом).  \n- Для e-ink это выглядит впечатляюще, хотя для видео всё равно не подойдёт.  \n- Основная ценность — работа на улице в ясную погоду, где обычные экраны бесполезны.  \n- Ноутбук с таким дисплеем мог бы стать отличным инструментом для программирования на свежем воздухе.",
  "sampleComments": [
    44873914,
    44874043
  ],
  "inputHash": "96b975fb1841470df46a0119e858c8c04016abb71d7dd1b85a220131966ef605",
  "model": "moonshotai/kimi-k2:free",
  "createdISO": "2025-08-12T09:27:40.719Z"
}