{
  "id": 44846781,
  "lang": "ru",
  "summary": "- Инженер без сильной математики спрашивает, с чего начать, чтобы самому реализовать Bezier-библиотеку.  \n- Обсуждают Rust-переписи PathBool.js и Graphite для булевых операций над кривыми.  \n- Пользователи ищут браузерные решения для stroke-expansion, рациональных Bezier в CAD и маршрутизации кривых вокруг препятствий.  \n- Рекомендуют видео Фреи Хольмёр, Solvespace, библиотеки skia/vello и WickEditor как альтернативные UI.  \n- Поднимают темы равномерной параметризации, 4-D анимации, OCaml/F# и удобства Quadratic-сплайнов в рисовалках.",
  "sampleComments": [
    44889517,
    44886800,
    44888089,
    44888465,
    44888217
  ],
  "inputHash": "432e8054578f1540f2a509b88f2dcb5ded86ea953f96f8da3394aaf51ee24e61",
  "model": "moonshotai/kimi-k2:free",
  "createdISO": "2025-08-13T15:24:39.647Z"
}