{
  "id": 44845957,
  "lang": "ru",
  "summary": "- Команда хотела быстро начать A/B-тесты, но вместо регистрации в SaaS ушли месяцы на корпоративные закупки.  \n- Большинство историй сводятся к тому, что «выгодные» оптовые скидки превращаются в переплату, когда ресурсы годами простаивают.  \n- Сравнение с продуктами в супермаркете: дешевле за единицу, но выгодно лишь если всё реально используешь.  \n- Примеры: закупка серверов на 3-5 лет вперёд, 7-летний контракт на 2 Мбит/с, когда уже доступен гигабит.  \n- Главная ловушка — уверенность в будущем спросе и давление продавцов, а не здравый расчёт.",
  "sampleComments": [
    44853016,
    44852234,
    44851434,
    44851303,
    44851830
  ],
  "inputHash": "15256f3a5ca9c593d393c3a0b817a432a1763a38d0a6e504630e5fdcbee02209",
  "model": "moonshotai/kimi-k2:free",
  "createdISO": "2025-08-10T11:23:46.277Z"
}