{
  "id": 44847903,
  "lang": "ru",
  "summary": "- Пользователи жалуются, что показ по одному слову сильно снижает скорость и не позволяет читать вперёд.  \n- Многие считают анимации и визуальные эффекты избыточными и отвлекающими.  \n- Кастомная клавиатура на мобильных устройствах слишком мелкая и неудобная; хотят возможности использовать системную.  \n- Отсутствуют альтернативные раскладки (Dvorak, Colemak) и настройки цвета/контраста.  \n- Неясно, когда именно запускается таймер, и почему не требуется backspace для исправления ошибок.  \n- Некоторые видят в тесте игру-«Guitar Hero» для печати и хвалят быструю обратную связь, но просят более плавный переход между уровнями сложности.",
  "sampleComments": [
    44886137,
    44886278,
    44887106,
    44886099,
    44887409
  ],
  "inputHash": "94bba9ccdb67b64791c7d6b354bb12e9e19868882335057c2d4408697fcfdcb2",
  "model": "moonshotai/kimi-k2:free",
  "createdISO": "2025-08-13T14:28:20.332Z"
}