{
  "id": 44846281,
  "lang": "ru",
  "summary": "- Проект показывает реалистичный цвет неба в реальном времени, используя научную модель рассеяния атмосферы.  \n- Пользователи в восторге: многие отмечают точное совпадение с видом из окна, особенно при ясной погоде.  \n- Ночью экран черный, что сбивает с толку и вызывает шутки про «баг» или «dark mode».  \n- Просят добавить учёт облаков, смога, светового загрязнения и возможность выбрать время/место.  \n- Несколько человек хотят сделать это живые обои рабочего стола или фон для «умного» дома.",
  "sampleComments": [
    44846565,
    44846473,
    44851449,
    44849432,
    44846687
  ],
  "inputHash": "0d6342e8bd6e597e7df41ea06bf869d7907294de5a1516dd678738b2935d618e",
  "model": "moonshotai/kimi-k2:free",
  "createdISO": "2025-08-10T05:27:39.632Z"
}