{
  "id": 44854035,
  "lang": "ru",
  "summary": "- Fish автоматически генерирует completion-файлы из man-страниц командой `fish_update_completions`.  \n- Bash- и zsh-пользователи жалуются на «умные» скрипты, которые иногда блокируют стандартное дополнение имён файлов.  \n- В ksh достаточно объявить массив `complete_command`, чтобы получить базовое дополнение.  \n- Для zsh существуют готовые хелперы `_gnu_generic` и генераторы по man-страницам, а также лёгкие one-liner-решения.  \n- Участники мечтают о едином стандарте вроде флага `--completion`, который бы автоматически поддерживали библиотеки парсинга аргументов.",
  "sampleComments": [
    44854235,
    44854384,
    44854992,
    44854164,
    44854971
  ],
  "inputHash": "20a2631d04a5d79f2ac255e47d57717a11f137c85f1b91ae8302b28d8b4744de",
  "model": "moonshotai/kimi-k2:free",
  "createdISO": "2025-08-10T13:32:18.709Z"
}