{
  "id": 44858692,
  "lang": "ru",
  "summary": "Если через пару секунд не перейдёте автоматически, нажмите [сюда](/httpservice/retry/enablejs?sei=MRyZaPKXFvO9vr0PupTdiAs).  \nПроблемы с доступом? [Попробуйте ещё раз](/search?q=Rupert+Grint&sca_esv=883831e2ccf399e3&hl=en&ie=UTF-8&emsg=SG_REL&sei=MRyZaPKXFvO9vr0PupTdiAs) или [напишите нам](https://support.google.com/websearch).",
  "inputHash": "41bae7f7bebbc11ce061537d11fbd2b0f9086c6c387479e01c393a76c94b21ab",
  "model": "moonshotai/kimi-k2:free",
  "createdISO": "2025-08-10T22:24:53.172Z"
}