{
  "id": 44858067,
  "lang": "ru",
  "summary": "- Участники сетуют, что 99 % современных сайтов выглядят одинаково: одни и те же шаблоны, шрифты, цвета, поп-апы.  \n- Предлагают собирать реальные скриншоты старых форумов и хостингов, чтобы сохранить «историю визуального веба».  \n- Некоторые уже годами делают личные архивы скриншотов и просят выложить их в открытый доступ.  \n- Инструмент полезен для вдохновения, но вызывает тревогу из-за однообразия дизайна.  \n- Появляются идеи использовать AI-фильтры для поиска «нишевых» или давно не менявшихся сайтов 90-х.",
  "sampleComments": [
    44859300,
    44858957,
    44858298,
    44858905,
    44858843
  ],
  "inputHash": "8ef91dc61ebc9a159c7755c726e8645f5840d07f6e51c57a0af2f518963e94c8",
  "model": "moonshotai/kimi-k2:free",
  "createdISO": "2025-08-10T23:23:03.859Z"
}