{
  "id": 44856426,
  "lang": "ru",
  "summary": "- ЕС тихо внедряет обязательную верификацию возраста на порносайтах с тюремным сроком до года (Amendment 186).  \n- Поправку внесли в последний момент, СМИ и НКО её почти не заметили.  \n- Совет ЕС продавливает инициативу, а позиции большинства евродепутатов всё ещё неясны.  \n- Политики ЕС исключили себя из-под слежки, сославшись на «профессиональную тайну».  \n- Комментаторы призывают писать депутатам, жертвовать проектам вроде GrapheneOS и переходить на децентрализованные/шифрованные средства связи.",
  "sampleComments": [
    44858081,
    44861953,
    44857738,
    44857422,
    44858549
  ],
  "inputHash": "774a58680cbe6208b7d53a79485fa848ca5f2e285fa08eb95c7b2e608e748c22",
  "model": "moonshotai/kimi-k2:free",
  "createdISO": "2025-08-11T08:39:50.071Z"
}