{
  "id": 44858009,
  "lang": "ru",
  "summary": "- React склонен сводить всё к состоянию, из-за чего приходится «зашивать» события в стейт (например, через usePrevious).  \n- Svelte с $state() и $effect() позволяет реагировать на изменения напрямую, минуя собственную систему событий и лишний boilerplate.  \n- Документация React советует избегать лишних эффектов и разделять «эффекты» и «события».  \n- Reducer-ы помогают, но при асинхронной обработке требуют много шаблонного кода и усложняют отладку.",
  "sampleComments": [
    44858248,
    44858526,
    44858010,
    44859241,
    44859190
  ],
  "inputHash": "aa7522ba2fac07b90f8e98ec46697d26acade77562e23d7212ad4355746bd36e",
  "model": "moonshotai/kimi-k2:free",
  "createdISO": "2025-08-10T23:24:14.769Z"
}