{
  "id": 44863753,
  "lang": "ru",
  "summary": "**TeaOnHer** — мужская версия популярного приложения **Tea** — течёт: открытая база AWS S3 содержит **> 120 000** водительских прав, селфи, паспортов и других документов пользователей.  \n\n- **Уязвимость**: папка `uploads/` доступна без авторизации; имена файлов предсказуемы.  \n- **Масштаб**: первые документы датированы июнем 2025 г.; ежедневно добавляются тысячи новых.  \n- **Реакция**: разработчики не ответили на запросы; Amazon уведомлена.  \n\nПриложение всё ещё доступно в App Store и продолжает собирать ID для «верификации».",
  "inputHash": "2141411052d7100307944bc24a5119dff663da4d5cf807c91669f66297acdd68",
  "model": "moonshotai/kimi-k2:free",
  "createdISO": "2025-08-11T14:28:53.610Z"
}