{
  "id": 44877201,
  "lang": "en",
  "tags": [
    {
      "name": "recto"
    },
    {
      "name": "programming-languages"
    },
    {
      "name": "2d-programming"
    },
    {
      "name": "visual-programming"
    },
    {
      "name": "recursion"
    },
    {
      "name": "github"
    },
    {
      "name": "google-colab"
    }
  ],
  "inputHash": "b857bcb1c70d67310f4f5bd2a8bcea1ee1e65fa3efcd3470ea2163bcf604ec46",
  "model": "mistralai/mistral-small-3.2-24b-instruct:free",
  "createdISO": "2025-08-16T01:56:37.127Z"
}