{
  "id": 44872984,
  "lang": "ru",
  "summary": "- Участники выясняли, что такое rerank-модели и зачем они нужны.  \n- Rerank-2.5-lite от VoyageAI — это модель, которая после «грубого» поиска (векторного или текстового) переупорядочивает найденные фрагменты по релевантности к запросу.  \n- Такая двухэтапная схема позволяет быстро отсеять лишнее, а затем точно выбрать самое релевантное.  \n- Некоторые удивлены, что модель выложена на Hugging Face, но наличие открытого токенизатора полезно: можно локально разбивать текст на чанки без обращения в интернет.",
  "sampleComments": [
    44893046,
    44894157,
    44893319,
    44893688,
    44894359
  ],
  "inputHash": "a06f09b40eeee203fc66085de374b7dfe7e06b53cd3295cd79773f6e8dd0cc22",
  "model": "moonshotai/kimi-k2:free",
  "createdISO": "2025-08-13T22:24:51.847Z"
}