{
  "id": 44888548,
  "lang": "ru",
  "summary": "- Пользователи наблюдают «галактические» вращения и спирали при прокрутке количества столбцов, особенно кратных 6.  \n- Найдены «пустые» диапазоны чисел при 546 столбцах из-за общих делителей с 546.  \n- Предложены новые функции: инверсия сетки (показ составных), старт с любого числа, фильтры по простым операциям, пропуск чётных и чисел, оканчивающихся на 5.  \n- Упомянуты Ulam spiral, 3Blue1Brown, Game of Life, Feistel-сети и «скрытое послание» для FTL-корабля.",
  "sampleComments": [
    44917090,
    44917720,
    44919537,
    44918710,
    44918742
  ],
  "inputHash": "fe8a6edc7a8142fc6e574a5a8489f08e7e0c9b655a462b2f8f7e420af91fcf16",
  "model": "moonshotai/kimi-k2:free",
  "createdISO": "2025-08-16T12:49:19.249Z"
}