{
  "id": 44881977,
  "lang": "ru",
  "summary": "- Вышел Go 1.25: новый пакет `encoding/json/v2` (флаг `GOEXPERIMENT=jsonv2`) ускоряет работу и позволяет писать кастомные маршалеры для внешних типов.  \n- Исправлена утечка памяти из блога Datadog (issue 72991).  \n- Появился экспериментальный сборщик «greentea» (issue 73581).  \n- LookupMX теперь принимает IP-адреса вместо доменных имён, если DNS-сервер так отвечает.  \n- Участники хвалят стабильность Go и быструю сборку старого кода, но жалуются на слабую документацию сторонних библиотек.",
  "sampleComments": [
    44883758,
    44884317,
    44882558,
    44882370,
    44883492
  ],
  "inputHash": "605f8450a1ba6529e8e42382784d1a58a16b80379e449a08f26f84143495b013",
  "model": "moonshotai/kimi-k2:free",
  "createdISO": "2025-08-13T03:25:45.992Z"
}