{
  "id": 44887965,
  "lang": "ru",
  "summary": "- Участники обсуждают, что плоттеры переживают второе рождение как инструмент для художников.  \n- Ключевой интерес — физические «несовершенства» линий, разводы чернил, возможность использовать маркеры, акварельные ручки и даже UV-чернилa.  \n- Несколько человек делятся опытом: кто-то уже рисует на Bantam Tools или самодельном Arduino-плоттере за ~100 $, другие советуют дешёвые Silhouette Portrait 2 и Cricut с насадками для ручек.  \n- Отдельно поднимается тема цвета: проф-принтеры могут иметь 8–12 красок, включая белую и специальные палитры, но «живые» случайности физического процесса всё равно сложно воспроизвести.",
  "sampleComments": [
    44890454,
    44888908,
    44890458,
    44890082,
    44888919
  ],
  "inputHash": "6c217c0acfe4c562f24023312848571523d27af9195df546ced0131d3e7b77f7",
  "model": "moonshotai/kimi-k2:free",
  "createdISO": "2025-08-13T16:26:53.291Z"
}