{
  "id": 44884393,
  "lang": "ru",
  "summary": "- Участники вспомнили упразднённый в 1966 г. «Индекс запрещённых книг» и иронизируют: теперь он выглядел бы как список «обязательного чтения».  \n- Некоторые католики считают запреты на чтение и мысль «бредом», другие — признают право церкви защищать паству от «злых идей».  \n- Упоминаются языковые каламбуры (фр. mettre à l’index), маркетинговый эффект попадания в список и даже рейды российского ОМОНа за «экстремистскую литературу».",
  "sampleComments": [
    44885671,
    44885501,
    44885210,
    44885322,
    44885357
  ],
  "inputHash": "cb59a74b39db1bcdbadfe26db6a5df11313815b5f480a1c9eec062fd7fce8940",
  "model": "moonshotai/kimi-k2:free",
  "createdISO": "2025-08-13T09:28:34.025Z"
}