{
  "id": 44887853,
  "lang": "ru",
  "summary": "- Ностальгия и лояльность: бывшие владельцы Pebble рады возвращению бренда и вспоминают, как первые часы помогали строить DigitalOcean и поддерживать связь с пользователями.  \n- Ключевые продукты: Pebble 2 Duo (149 $, ч/б, классический вид) и Pebble Time 2 (225 $, цветной экран, новый дизайн); обещают 30 дней автономности, IPX8 и совместимость со старыми приложениями.  \n- Сомнения и сравнения: часть аудитории считает, что Garmin/Epix с AMOLED и месяцем работы перекрывают потребности; другие жалуются на отсутствие GPS, NFC-платежей и сомневаются в контрастности цветного экрана.  \n- Дизайн и эргономика: одни хвалят «стар-трек»-внешность, другие называют её безликой и просят компактную версию для узких запястий.  \n- Разработка и ремонт: спрашивают SDK, документацию, ремонтопригодность и возможность замены батареи; волнуются, что корпус снова склеен.  \n- Подписки и экосистема: критика Garmin за платные функции и закрытость; Pebble позиционируют как открытую, «не навязчивую» альтернативу без облачных подписок.",
  "sampleComments": [
    44892545,
    44891722,
    44894459,
    44889266,
    44891310
  ],
  "inputHash": "250b54a68a88b16f9cd585687ca5cb9c2af70b88457fc7dff515a4f3b5669d05",
  "model": "moonshotai/kimi-k2:free",
  "createdISO": "2025-08-13T22:25:07.642Z"
}