{
  "id": 44881109,
  "lang": "ru",
  "summary": "Книга _10 PRINT_ (2012) исследует однострочную BASIC-программу для Commodore 64, рассматривая код как культурный текст. Десять авторов анализируют случайность и порядок в вычислениях и искусстве, лабиринт в культуре, язык BASIC и сам компьютер C64.  \n\n**Где купить/скачать**  \n- Бумажное издание: [MIT Press](https://mitpress.mit.edu/9780262526746), Alibris, ISBN.nu.  \n- [PDF 50 МБ](10_PRINT_121114.pdf) под лицензией CC BY-NC-SA 3.0.  \n\n**Материалы и вдохновение**  \n- Фото книги и дизайн: [reas.com/10_print](https://reas.com/10_print).  \n- Образец диска C64: [nickm.com/post/2014/06/a-companion-disk-for-10-print](https://nickm.com/post/2014/06/a-companion-disk-for-10-print).  \n- Посты: [Nick Montfort](http://nickm.com/post/tag/10-print/), [Mark Sample](http://www.samplereality.com/tag/10-print/).  \n- Хэштег [#10print](https://twitter.com/search?q=%2310print) и бот [@10_PAINT](https://twitter.com/10_PAINT).  \n- Обучение: [The Coding Train](https://www.youtube.com/watch?v=bEyTZ5ZZxZs).  \n- Дизайн: обложки NYPL, генеративные часы, принты Casey Reas.  \n- Арт: _Adventures in 10 Print_, демосцена (от 42 до 12 байт), JS-версия “Thread JS”.  \n\n**Рецензии**  \nSlate, Neural, Technology Review, Enculturation; вошла в список лучших книг о видеоиграх PC Gamer.",
  "inputHash": "1face643ef89279c306360cf661bf7fcf30df833544be016485911aa53a53044",
  "model": "moonshotai/kimi-k2:free",
  "createdISO": "2025-08-14T03:27:32.165Z"
}