{
  "id": 44899339,
  "lang": "ru",
  "summary": "- Новый белок RcoM-HBD-CCC связывает CO в крови за <1 мин, тогда как кислород требует >1 ч, а без лечения — 5 ч.  \n- Вводится внутривенно; последовательность и 6×His-тег приведены в дополнении.  \n- Обсуждение: метиленовый синий спорен для CO-отравления, но применяется при метгемоглобинемии.  \n- Альтернативы: гипербарическая кислородная терапия и даже «дайвинг-лечение».",
  "sampleComments": [
    44903420,
    44901970,
    44903358,
    44901440,
    44901041
  ],
  "inputHash": "95ee1de0b2585486f8964e1c63bacc2206ab4f7174dfb0fc7adb68ca5c41c4d8",
  "model": "moonshotai/kimi-k2:free",
  "createdISO": "2025-08-14T22:23:45.288Z"
}