{
  "id": 44892209,
  "lang": "ru",
  "summary": "- Участники обсуждают новый продукт Pyx от Astral — частный, платный реестр пакетов Python с «GPU-aware»-функциями.  \n- Многие опасаются VC-финансирования и возможного «cash-out»: истории с внезапными закрытиями проектов и удалением данных повторяются.  \n- Утверждается, что Pyx должен решить боль установки CUDA-зависимых библиотек, но критики считают это очередным коммерческим «training wheels».  \n- Раздражение вызывает и само имя «pyx» (коллизия с Cython) и ощущение, что появился «ещё один» инструмент в уже перегруженной экосистеме.  \n- Пользователи сравнивают опыт с Go/NodeJS, жалуются на десятки способов установки пакетов и задаются вопросом, нужен ли вообще ещё один стандарт.",
  "sampleComments": [
    44894063,
    44892499,
    44893239,
    44896240,
    44892578
  ],
  "inputHash": "3d0d684df01fc212894e593b2557fe2a384813ab7575d0aa52fd8a3d3bf5cf26",
  "model": "moonshotai/kimi-k2:free",
  "createdISO": "2025-08-14T05:24:43.924Z"
}