{
  "id": 44892283,
  "lang": "ru",
  "summary": "- Участники спорят, станет ли ИИ массово вытеснять людей или породит новые виды занятости.  \n- Сторонники «plateau» считают рост способностей моделей замедлившимся; скептики указывают на уже заметное сокращение низкоквалифицированных административных ролей.  \n- Главный страх — экономическая система не выдержит, если ИИ быстрее переучивается, чем люди, и компании перестанут покупать внешние сервисы.  \n- Некоторые предлагают UBI или иные альтернативы рыночному устройству; другие напоминают, что раньше каждая технологическая волна в итоге увеличивала общее благосостояние.  \n- Общий вывод: прогнозы строятся в будущем времени без достаточных данных, а реальный эффект ИИ пока сильно зависит от скорости его внедрения и политических решений.",
  "sampleComments": [
    44924213,
    44921941,
    44919588,
    44919860,
    44920295
  ],
  "inputHash": "0d68c1ae0bdcfbafb7b2a1c43b2a2ca5a3a0e09b507f9e8090cae277e3af0b11",
  "model": "moonshotai/kimi-k2:free",
  "createdISO": "2025-08-16T15:23:14.898Z"
}