{
  "id": 44891509,
  "lang": "ru",
  "summary": "- В 2014 году «шуточный» пост о «Real TDD» (писать только тесты, код пишет компьютер) воспринимался как фантастика.  \n- Спустя 10 лет мы реально генерируем и код, и тесты без участия человека («vibecode»).  \n- Участники отмечают, как быстро сместились ожидания: AGI-мишени 2010 года уже кажутся скромными.  \n- Сравнивают с Pixar, которые в 90-х шутили о рендере еды, а потом реализовали это в «Ratatouille».  \n- Итог: будущее пришло раньше, чем предполагали даже его изобретатели.",
  "sampleComments": [
    44891925,
    44892595,
    44891908,
    44892272,
    44893063
  ],
  "inputHash": "4d3b2c7eefb37669b2a9f59d807a3945dadebf381ebe62859329b4f7fef2dd04",
  "model": "moonshotai/kimi-k2:free",
  "createdISO": "2025-08-13T20:29:20.530Z"
}