{
  "id": 44901683,
  "lang": "ru",
  "summary": "- @lucfranken: при переключении из режима редактирования в просмотр красные линии редактирования остаются активными, мешают скроллу; помогает только перезагрузка.  \n- @billconan: раньше использовал pdf.js, но зум был медленным; перешёл на pdfium + Metal + тайлинг — получилось быстро и плавно (видео-демо).  \n- @lysace: репозиторий содержит копию pdfium.js, UI и слои-обёртки для разных JS-фреймворков?  \n- @bobsingor: ваш зум ещё шустрее, вдохновляет вернуться к оптимизации своего решения.",
  "sampleComments": [
    44903031,
    44901801,
    44903045,
    44902598
  ],
  "inputHash": "5869ccef13e6f23917c132ed86a838941406dd9e7ecc10b5eb3a995a744fdc8a",
  "model": "moonshotai/kimi-k2:free",
  "createdISO": "2025-08-14T17:24:40.928Z"
}