{
  "id": 44907531,
  "lang": "ru",
  "summary": "- Многие изучающие японский и китайский сознательно отказываются от рукописного письма, считая его отдельным, ненужным навыком.  \n- Даже носители всё чаще страдают «забыванием иероглифов» (提笔忘字 / 漢字健忘) из-за постоянного использования пиньинь- или ромадзи-ввода.  \n- Разделение «читать могу — писать не могу» стало мемом и даже темой телешоу в Японии.  \n- Некоторые отмечают, что умение писать помогает различать похожие иероглифы при чтении, но затраты времени не оправдывают пользы.  \n- Обсуждаются возможные последствия: упрощение системы, переход к фонетическим слоговым азбукам или сохранение статус-кво благодаря компьютерам.",
  "sampleComments": [
    44907897,
    44908487,
    44908691,
    44908741,
    44908319
  ],
  "inputHash": "53d4a6d7ffd60a2140dd396bef51cb372c1c8cfe755d1e5f0350bf27b1368bec",
  "model": "moonshotai/kimi-k2:free",
  "createdISO": "2025-08-15T06:36:52.806Z"
}