{
  "id": 44909133,
  "lang": "ru",
  "summary": "- Участники хвалят интерактивные симуляции как способ «почувствовать» ЦПТ до изучения формул.  \n- Обсуждаются обобщения: аналог для экстремумов (Fisher–Tippett–Gnedenko), теорема для распределений без дисперсии и связь с тяжёлыми хвостами.  \n- Подчёркивают, что «классическая» ЦПТ требует осторожности: сходимость может быть медленной, а реальные данные нарушают её предпосылки.  \n- Упомянуты полезные ресурсы: 3Blue1Brown, книга «The Fundamentals of Heavy Tails», посты Тао и статьи на arXiv.  \n- Разгорелся спор о стиле кода tidyverse и о том, стоит ли помечать AI-помощь в статьях.",
  "sampleComments": [
    44913071,
    44911265,
    44909520,
    44912094,
    44911441
  ],
  "inputHash": "dcf9f701bb3f5616556b9209153ceee61c06fe1232b91c12c8c958591d59b3f4",
  "model": "moonshotai/kimi-k2:free",
  "createdISO": "2025-08-15T15:26:12.990Z"
}