{
  "id": 44900455,
  "lang": "ru",
  "summary": "- Пользователи хвалят Jujutsu за низкий порог входа и удобный workflow, особенно при работе со сложными ветками.  \n- Некоторые уже полностью перешли на megamerge-подход и считают его лучше Git.  \n- Вопросы касаются интеграции с системами ревью (GitHub) и ожидания поддержки сабмодулей.  \n- Сторонники Git считают, что «проблемы» Jujutsu надуманы или уже решены в новых версиях Git.  \n- Те, кто пробовал, отмечают, что `jj git push` позволяет открывать PR как обычно, но автоматически обновляет зависимые ветки.",
  "sampleComments": [
    44901747,
    44901223,
    44901184,
    44901280,
    44900619
  ],
  "inputHash": "ad62dd101b698379751dec9cc65d152041032fbf19a55538ded9f66c6beae9fc",
  "model": "moonshotai/kimi-k2:free",
  "createdISO": "2025-08-14T16:32:21.582Z"
}