{
  "id": 44910865,
  "lang": "ru",
  "summary": "- Автор статьи высмеял убогий официальный PureGym-приложение и показал, как выкрутился из ситуации, сделав собственный Apple Wallet-пасс с обновляемым QR-кодом.  \n- Комментаторы подтвердили: приложение тормозит, глушит фоновое аудио и по сути является обёрткой над сайтом, а PIN-коды генерируются предсказуемо и не защищены от перебора.  \n- Обсуждали, почему компании не делают нормальный Wallet-пасс: дорого поддерживать, никто не хочет «владеть» фичей, а приоритет — подписки, а не UX.  \n- Некоторые просто выучили PIN и заходят быстрее, чем любое приложение; другие делятся лайфхаками вроде Pass2Wallet или самодельных pkpass-файлов.",
  "sampleComments": [
    44918499,
    44923320,
    44921612,
    44920291,
    44921807
  ],
  "inputHash": "e10e45a527236a1264ebad4189c788db609df9bcfd53aa620763b745e9db2447",
  "model": "moonshotai/kimi-k2:free",
  "createdISO": "2025-08-16T14:20:44.666Z"
}