{
  "id": 44915824,
  "lang": "en",
  "tags": [
    {
      "name": "openbsd"
    },
    {
      "name": "linux"
    },
    {
      "name": "benchmarking"
    },
    {
      "name": "performance"
    },
    {
      "name": "sockets"
    },
    {
      "name": "file-descriptors"
    },
    {
      "name": "security"
    },
    {
      "name": "rdtsc"
    }
  ],
  "inputHash": "a1d293979aa0b8757af8493823e4fff1f2991ff2e9c05b401c7a2cf9ba35bd68",
  "model": "mistralai/mistral-small-3.2-24b-instruct:free",
  "createdISO": "2025-08-16T18:35:24.021Z"
}