{
  "id": 44915824,
  "lang": "en",
  "tags": [
    {
      "name": "openbsd"
    },
    {
      "name": "linux"
    },
    {
      "name": "benchmarking"
    },
    {
      "name": "performance"
    },
    {
      "name": "multithreading"
    },
    {
      "name": "sockets"
    },
    {
      "name": "file-descriptors"
    },
    {
      "name": "security"
    }
  ],
  "inputHash": "19724c0b8941dbfb5680bd0835cd6e96cfabf0bc9663d46bc81132d878396bd0",
  "model": "mistralai/mistral-small-3.2-24b-instruct:free",
  "createdISO": "2025-08-16T12:47:17.575Z"
}