{
  "id": 44911941,
  "lang": "ru",
  "summary": "- Пользователи спорят, стало ли авиаперелёт «хуже»: кто-то фиксирует постоянные задержки, кто-то — рост цен и ухудшение сервиса.  \n- Главные причины задержек называют «запас времени» в расписании для статистики пунктуальности, плату за багаж (из-за неё все несут ручную кладь) и медленную выдачу багажа.  \n- Бюджетные авиакомпании Европы быстро садят/высаживают пассажиров, но экономят за счёт комфорта и питания.  \n- Многие жалуются на «армейские» условия: теснота, потерянные чемоданы, хамство персонала.  \n- Часть участников считает, что «дешевле стало» только на бумаге: базовый тариф низкий, но всё остальное платное.",
  "sampleComments": [
    44918814,
    44915866,
    44915225,
    44918984,
    44916526
  ],
  "inputHash": "e0c43e1d11c53ceb4f5134dc8cf784308c0e4608320eeb0c2c648bc830df7f4d",
  "model": "moonshotai/kimi-k2:free",
  "createdISO": "2025-08-16T07:34:07.880Z"
}