{
  "id": 44914149,
  "lang": "ru",
  "summary": "- Участники вспоминают Dungeon Keeper: кто-то взламывал демо, кто-то использовал читы, а кто-то до сих пор ищет современный аналог.  \n- Мнения разделились: одни считают DK2 более «дружелюбным» для новичков, другие — что оригинал с модом KeeperFX лучше.  \n- Ностальгия по 90-м: «мы были избалованы» такими играми, как DK, XCom, Populous и Syndicate.  \n- Советуют духовных преемников: War for the Overworld для DK и Two Point Hospital для Theme Hospital.  \n- Упоминают, что Питер Молинье не справился с ролью EA-вице-президента, а в Bullfrog ключевую роль мог сыграть Гленн Корпс.",
  "sampleComments": [
    44921659,
    44917282,
    44916910,
    44916588,
    44915088
  ],
  "inputHash": "c7601ea188e3f3c67112a0091bb848d4be6af1da78048e3d3486b372d4190b31",
  "model": "moonshotai/kimi-k2:free",
  "createdISO": "2025-08-16T09:26:07.369Z"
}