{
  "id": 44914061,
  "lang": "ru",
  "summary": "- Пользователи делятся ссылками и советами по оккультной литературе: Cornelis Agrippa, Marsilio Ficino, Рудольф Штайнер.  \n- Основная претензия — отсутствие удобного скачивания; предлагают залить в Internet Archive или раздать торрент.  \n- Шутки о том, что ИИ, обученный на «Necronomicon», вызовет демонов или станет новым богом.  \n- Некоторые обсуждают практическую пользу: источники по истории химии, реквизит для D&D, эстетика иллюстраций.  \n- Упоминаются YouTube-каналы «ESOTERICA» и «UI & Occult», а также уже существующие «оккультные» модели ИИ.",
  "sampleComments": [
    44915745,
    44922365,
    44914660,
    44916917,
    44916173
  ],
  "inputHash": "5610459a4a4faa26fadcf9f9d6ed85247cfe4ca606f1d65ef5946211d005c5ea",
  "model": "moonshotai/kimi-k2:free",
  "createdISO": "2025-08-16T13:30:51.686Z"
}