{
  "id": 44925597,
  "lang": "en",
  "tags": [
    {
      "name": "rust"
    },
    {
      "name": "epub"
    },
    {
      "name": "text-to-speech"
    },
    {
      "name": "terminal"
    },
    {
      "name": "vim"
    },
    {
      "name": "linux"
    },
    {
      "name": "macos"
    },
    {
      "name": "windows"
    },
    {
      "name": "mit"
    },
    {
      "name": "python"
    }
  ],
  "inputHash": "bfbae84c1d8f4736fc17c3bdb9dc8854f369108763e028868f74f5f6f14ef2ae",
  "model": "mistralai/mistral-small-3.2-24b-instruct:free",
  "createdISO": "2025-08-16T20:24:30.636Z"
}