[
  {
    "id": 44789191,
    "by": "dv_dt",
    "timeISO": "2025-08-04T17:50:03.000Z",
    "textPlain": "Lol, I have been exploring in the opposite direction.  Given a set of basic CRUD endpoints for various data structures, including links to other structures. Generate a basic UI for them, with guidance on added ui to generate based on input and data oriented interaction specs.This is cool though, I think there are going to be an explosion of different higher level development patterns that will be useful in a lot of different situations that AI  will enable. It will be interesting to see which ones get wider adoption, and which stay useful but in smaller focused niches.",
    "parent": 44785292,
    "depth": 1
  },
  {
    "id": 44788705,
    "by": "_fat_santa",
    "timeISO": "2025-08-04T17:13:10.000Z",
    "textPlain": "At my org we have been using the Figma MCP server to generate code from Figma designs. Spent about a day writing rules to keep the AI on guardrails but it's been very smooth sailing since then and any generated code needs minimal changes.",
    "parent": 44785292,
    "depth": 1
  },
  {
    "id": 44787093,
    "by": "wiradikusuma",
    "timeISO": "2025-08-04T15:21:53.000Z",
    "textPlain": "I guess it's good for \"Dreamweaver 2.0\" in the sense that it produces plain HTML. But my understanding is most serious web applications use a framework of some sort, such as React, Vue, or Svelte, and each is opinionated.",
    "parent": 44785292,
    "depth": 1
  },
  {
    "id": 44787364,
    "by": "kocial",
    "timeISO": "2025-08-04T15:40:58.000Z",
    "textPlain": "Oh! What about CSS frameworks like Tailwind, Bootstrap, etc.?How on earth was it able to generate and clone Images just from UI? Like did it get the source of the URL as well, where it could link those images or what did it actually do there?",
    "parent": 44785292,
    "depth": 1
  },
  {
    "id": 44789505,
    "by": "vivzkestrel",
    "timeISO": "2025-08-04T18:11:52.000Z",
    "textPlain": "Would be nice if it generated HTMX",
    "parent": 44785292,
    "depth": 1
  }
]