[
  {
    "id": 44807814,
    "by": "userbinator",
    "timeISO": "2025-08-06T04:57:14.000Z",
    "textPlain": "09 F9 11...Too bad these certificates are a bit long to memorise, but no doubt Streisand Effect will have already happened.Meanwhile the \"true\" pirates still win, with no accounts to suspend.",
    "parent": 44807480,
    "depth": 1
  },
  {
    "id": 44817542,
    "by": "drewbitt",
    "timeISO": "2025-08-06T20:40:29.000Z",
    "textPlain": "It has been cracked for years among the scene, this is just the spreading of some certs publicly.",
    "parent": 44807480,
    "depth": 1
  },
  {
    "id": 44808235,
    "by": "DoctorOW",
    "timeISO": "2025-08-06T06:01:25.000Z",
    "textPlain": "If these certificates were actively being used when they were leaked, are they sure that they only banned people circumventing DRM? How do they roll out new certs?",
    "parent": 44807480,
    "depth": 1
  },
  {
    "id": 44808792,
    "by": "trallnag",
    "timeISO": "2025-08-06T07:25:31.000Z",
    "textPlain": "Events like this show the advantages of a multi-polar world. For example, servers in Russia usually form a safe haven for material like this. Or at least a \"safer\" haven. The same is true the other way around. Content that is factually prohibited in Russia can be published in the EU. One good example for this is, TV Rain, a Russian media outlet I support and really like. They face prosecution in Russia and are now located in the Netherlands.",
    "parent": 44807480,
    "depth": 1
  }
]