[
  {
    "id": 44864310,
    "by": "trimbo",
    "timeISO": "2025-08-11T14:14:45.000Z",
    "textPlain": "Real miss by the NYT here in not finding and interviewing people who were still using it in 2025!",
    "parent": 44861521,
    "depth": 1
  },
  {
    "id": 44864413,
    "by": "layer8",
    "timeISO": "2025-08-11T14:21:36.000Z",
    "textPlain": "Previous discussion two days ago, 101 comments: https://news.ycombinator.com/item?id=44843369",
    "parent": 44861521,
    "depth": 1
  },
  {
    "id": 44864305,
    "by": "jonathaneunice",
    "timeISO": "2025-08-11T14:14:32.000Z",
    "textPlain": "TIL AOL still offered dial-up internet.At long last, the 1990s will soon come to an end.",
    "parent": 44861521,
    "depth": 1
  },
  {
    "id": 44864304,
    "by": "hopelite",
    "timeISO": "2025-08-11T14:14:31.000Z",
    "textPlain": "I’ve always wondered about the remaining users of the dial-up service. Who are they and what is the use case for using dial-up?Does anyone know?",
    "parent": 44861521,
    "depth": 1
  },
  {
    "id": 44864348,
    "by": "dfedbeef",
    "timeISO": "2025-08-11T14:17:12.000Z",
    "textPlain": "TIL AOL still exists",
    "parent": 44864305,
    "depth": 2
  },
  {
    "id": 44864326,
    "by": "imzadi",
    "timeISO": "2025-08-11T14:15:42.000Z",
    "textPlain": "Probably people in rural areas that have limited access to other options. Starlink has probably absorbed most of that market, so no need to have dial up anymore.",
    "parent": 44864304,
    "depth": 2
  },
  {
    "id": 44864442,
    "by": "scarface_74",
    "timeISO": "2025-08-11T14:23:55.000Z",
    "textPlain": "It couldn’t be too many people.  Back in 2015, they only had 2.1 million dial up users and that number must have gone down in a decadehttps://www.usatoday.com/story/tech/2025/08/10/aol-dial-up-i...But then again, I would love to have a business that has 2.1 million people or even 100 thousand people paying $10 a month…",
    "parent": 44864304,
    "depth": 2
  },
  {
    "id": 44864376,
    "by": "johnwheeler",
    "timeISO": "2025-08-11T14:18:58.000Z",
    "textPlain": "Senior citizens who don’t know any better and never upgraded.then in their 50s now in their 70-80s.",
    "parent": 44864304,
    "depth": 2
  }
]